shared_image_processing/__init__.py
shared_image_processing/connectedComponents.py
shared_image_processing/enhancement.py
shared_image_processing/features.py
shared_image_processing-0.0.2.dist-info/METADATA
shared_image_processing-0.0.2.dist-info/WHEEL
shared_image_processing-0.0.2.dist-info/top_level.txt
shared_image_processing-0.0.2.dist-info/RECORD
